{
  "path": "/docs/developer-resources/guides",
  "previousText": "Courses",
  "previousUrl": "/docs/developer-resources/courses",
  "nextText": "Posts",
  "nextUrl": "/docs/developer-resources/posts",
  "body": [
    "div",
    null,
    [
      "h3",
      {
        "id": "your-first-ionic-app-v3"
      },
      " ",
      [
        "a",
        {
          "href": "#your-first-ionic-app-v3"
        },
        [
          "stencil-route-link",
          {
            "url": "/docs/developer-resources/guides/first-app-v3/intro"
          },
          "Your First Ionic App - v3"
        ]
      ],
      " "
    ],
    " ",
    [
      "p",
      null,
      "Follow along as we create a working Photo Gallery app using Ionic Framework v3 and Ionic Appflow."
    ],
    " ",
    [
      "h3",
      {
        "id": "your-first-ionic-4-app-angular-and-cordova"
      },
      " ",
      [
        "a",
        {
          "href": "#your-first-ionic-4-app-angular-and-cordova"
        },
        [
          "stencil-route-link",
          {
            "url": "/docs/developer-resources/guides/first-app-v4/intro"
          },
          "Your First Ionic 4 App - Angular and Cordova"
        ]
      ],
      " "
    ],
    " ",
    [
      "p",
      null,
      "Follow along as we create a working Photo Gallery app using Ionic Framework v4 and Cordova."
    ]
  ],
  "title": "Guides",
  "headings": [],
  "pageClass": "page-developer-resources-guides"
}
