{
  "title": "Zeroconf",
  "path": "/docs/native/zeroconf",
  "body": [
    "div",
    null,
    [
      "p",
      {
        "class": "intro"
      },
      "This plugin allows you to browse and publish Zeroconf/Bonjour/mDNS services."
    ]
  ],
  "repo": "https://github.com/becvert/cordova-plugin-zeroconf",
  "platforms": [
    "Android",
    "iOS"
  ],
  "codeUsage": [
    "div",
    null,
    [
      "docs-code",
      {
        "language": "typescript"
      },
      "\n  ",
      [
        "pre",
        null,
        [
          "code",
          null,
          [
            "span",
            {
              "class": "token keyword"
            },
            "import"
          ],
          " ",
          [
            "span",
            {
              "class": "token punctuation"
            },
            "{"
          ],
          " Zeroconf ",
          [
            "span",
            {
              "class": "token punctuation"
            },
            "}"
          ],
          " ",
          [
            "span",
            {
              "class": "token keyword"
            },
            "from"
          ],
          " ",
          [
            "span",
            {
              "class": "token string"
            },
            "'@ionic-native/zeroconf/ngx'"
          ],
          [
            "span",
            {
              "class": "token punctuation"
            },
            ";"
          ],
          "\n\n",
          [
            "span",
            {
              "class": "token keyword"
            },
            "constructor"
          ],
          [
            "span",
            {
              "class": "token punctuation"
            },
            "("
          ],
          [
            "span",
            {
              "class": "token parameter"
            },
            [
              "span",
              {
                "class": "token keyword"
              },
              "private"
            ],
            " zeroconf",
            [
              "span",
              {
                "class": "token operator"
              },
              ":"
            ],
            " Zeroconf"
          ],
          [
            "span",
            {
              "class": "token punctuation"
            },
            ")"
          ],
          " ",
          [
            "span",
            {
              "class": "token punctuation"
            },
            "{"
          ],
          " ",
          [
            "span",
            {
              "class": "token punctuation"
            },
            "}"
          ],
          "\n\n",
          [
            "span",
            {
              "class": "token operator"
            },
            "..."
          ],
          "\n\n",
          [
            "span",
            {
              "class": "token comment"
            },
            "// watch for services of a specified type"
          ],
          "\n",
          [
            "span",
            {
              "class": "token keyword"
            },
            "this"
          ],
          [
            "span",
            {
              "class": "token punctuation"
            },
            "."
          ],
          "zeroconf",
          [
            "span",
            {
              "class": "token punctuation"
            },
            "."
          ],
          [
            "span",
            {
              "class": "token function"
            },
            "watch"
          ],
          [
            "span",
            {
              "class": "token punctuation"
            },
            "("
          ],
          [
            "span",
            {
              "class": "token string"
            },
            "'_http._tcp.'"
          ],
          [
            "span",
            {
              "class": "token punctuation"
            },
            ","
          ],
          " ",
          [
            "span",
            {
              "class": "token string"
            },
            "'local.'"
          ],
          [
            "span",
            {
              "class": "token punctuation"
            },
            ")"
          ],
          [
            "span",
            {
              "class": "token punctuation"
            },
            "."
          ],
          [
            "span",
            {
              "class": "token function"
            },
            "subscribe"
          ],
          [
            "span",
            {
              "class": "token punctuation"
            },
            "("
          ],
          [
            "span",
            {
              "class": "token parameter"
            },
            "result"
          ],
          " ",
          [
            "span",
            {
              "class": "token operator"
            },
            "=>"
          ],
          " ",
          [
            "span",
            {
              "class": "token punctuation"
            },
            "{"
          ],
          "\n  ",
          [
            "span",
            {
              "class": "token keyword"
            },
            "if"
          ],
          " ",
          [
            "span",
            {
              "class": "token punctuation"
            },
            "("
          ],
          "result",
          [
            "span",
            {
              "class": "token punctuation"
            },
            "."
          ],
          "action ",
          [
            "span",
            {
              "class": "token operator"
            },
            "=="
          ],
          " ",
          [
            "span",
            {
              "class": "token string"
            },
            "'added'"
          ],
          [
            "span",
            {
              "class": "token punctuation"
            },
            ")"
          ],
          " ",
          [
            "span",
            {
              "class": "token punctuation"
            },
            "{"
          ],
          "\n    ",
          [
            "span",
            {
              "class": "token builtin"
            },
            "console"
          ],
          [
            "span",
            {
              "class": "token punctuation"
            },
            "."
          ],
          [
            "span",
            {
              "class": "token function"
            },
            "log"
          ],
          [
            "span",
            {
              "class": "token punctuation"
            },
            "("
          ],
          [
            "span",
            {
              "class": "token string"
            },
            "'service added'"
          ],
          [
            "span",
            {
              "class": "token punctuation"
            },
            ","
          ],
          " result",
          [
            "span",
            {
              "class": "token punctuation"
            },
            "."
          ],
          "service",
          [
            "span",
            {
              "class": "token punctuation"
            },
            ")"
          ],
          [
            "span",
            {
              "class": "token punctuation"
            },
            ";"
          ],
          "\n  ",
          [
            "span",
            {
              "class": "token punctuation"
            },
            "}"
          ],
          " ",
          [
            "span",
            {
              "class": "token keyword"
            },
            "else"
          ],
          " ",
          [
            "span",
            {
              "class": "token punctuation"
            },
            "{"
          ],
          "\n    ",
          [
            "span",
            {
              "class": "token builtin"
            },
            "console"
          ],
          [
            "span",
            {
              "class": "token punctuation"
            },
            "."
          ],
          [
            "span",
            {
              "class": "token function"
            },
            "log"
          ],
          [
            "span",
            {
              "class": "token punctuation"
            },
            "("
          ],
          [
            "span",
            {
              "class": "token string"
            },
            "'service removed'"
          ],
          [
            "span",
            {
              "class": "token punctuation"
            },
            ","
          ],
          " result",
          [
            "span",
            {
              "class": "token punctuation"
            },
            "."
          ],
          "service",
          [
            "span",
            {
              "class": "token punctuation"
            },
            ")"
          ],
          [
            "span",
            {
              "class": "token punctuation"
            },
            ";"
          ],
          "\n  ",
          [
            "span",
            {
              "class": "token punctuation"
            },
            "}"
          ],
          "\n",
          [
            "span",
            {
              "class": "token punctuation"
            },
            "}"
          ],
          [
            "span",
            {
              "class": "token punctuation"
            },
            ")"
          ],
          [
            "span",
            {
              "class": "token punctuation"
            },
            ";"
          ],
          "\n\n",
          [
            "span",
            {
              "class": "token comment"
            },
            "// publish a zeroconf service of your own"
          ],
          "\n",
          [
            "span",
            {
              "class": "token keyword"
            },
            "this"
          ],
          [
            "span",
            {
              "class": "token punctuation"
            },
            "."
          ],
          "zeroconf",
          [
            "span",
            {
              "class": "token punctuation"
            },
            "."
          ],
          [
            "span",
            {
              "class": "token function"
            },
            "register"
          ],
          [
            "span",
            {
              "class": "token punctuation"
            },
            "("
          ],
          [
            "span",
            {
              "class": "token string"
            },
            "'_http._tcp.'"
          ],
          [
            "span",
            {
              "class": "token punctuation"
            },
            ","
          ],
          " ",
          [
            "span",
            {
              "class": "token string"
            },
            "'local.'"
          ],
          [
            "span",
            {
              "class": "token punctuation"
            },
            ","
          ],
          " ",
          [
            "span",
            {
              "class": "token string"
            },
            "'Becvert\\'s iPad'"
          ],
          [
            "span",
            {
              "class": "token punctuation"
            },
            ","
          ],
          " ",
          [
            "span",
            {
              "class": "token number"
            },
            "80"
          ],
          [
            "span",
            {
              "class": "token punctuation"
            },
            ","
          ],
          " ",
          [
            "span",
            {
              "class": "token punctuation"
            },
            "{"
          ],
          "\n  ",
          [
            "span",
            {
              "class": "token string"
            },
            "'foo'"
          ],
          [
            "span",
            {
              "class": "token operator"
            },
            ":"
          ],
          " ",
          [
            "span",
            {
              "class": "token string"
            },
            "'bar'"
          ],
          "\n",
          [
            "span",
            {
              "class": "token punctuation"
            },
            "}"
          ],
          [
            "span",
            {
              "class": "token punctuation"
            },
            ")"
          ],
          [
            "span",
            {
              "class": "token punctuation"
            },
            "."
          ],
          [
            "span",
            {
              "class": "token function"
            },
            "then"
          ],
          [
            "span",
            {
              "class": "token punctuation"
            },
            "("
          ],
          [
            "span",
            {
              "class": "token parameter"
            },
            "result"
          ],
          " ",
          [
            "span",
            {
              "class": "token operator"
            },
            "=>"
          ],
          " ",
          [
            "span",
            {
              "class": "token punctuation"
            },
            "{"
          ],
          "\n  ",
          [
            "span",
            {
              "class": "token builtin"
            },
            "console"
          ],
          [
            "span",
            {
              "class": "token punctuation"
            },
            "."
          ],
          [
            "span",
            {
              "class": "token function"
            },
            "log"
          ],
          [
            "span",
            {
              "class": "token punctuation"
            },
            "("
          ],
          [
            "span",
            {
              "class": "token string"
            },
            "'Service registered'"
          ],
          [
            "span",
            {
              "class": "token punctuation"
            },
            ","
          ],
          " result",
          [
            "span",
            {
              "class": "token punctuation"
            },
            "."
          ],
          "service",
          [
            "span",
            {
              "class": "token punctuation"
            },
            ")"
          ],
          [
            "span",
            {
              "class": "token punctuation"
            },
            ";"
          ],
          "\n",
          [
            "span",
            {
              "class": "token punctuation"
            },
            "}"
          ],
          [
            "span",
            {
              "class": "token punctuation"
            },
            ")"
          ],
          [
            "span",
            {
              "class": "token punctuation"
            },
            ";"
          ],
          "\n\n\n",
          [
            "span",
            {
              "class": "token comment"
            },
            "// unregister your service"
          ],
          "\n",
          [
            "span",
            {
              "class": "token keyword"
            },
            "this"
          ],
          [
            "span",
            {
              "class": "token punctuation"
            },
            "."
          ],
          "zeroconf",
          [
            "span",
            {
              "class": "token punctuation"
            },
            "."
          ],
          [
            "span",
            {
              "class": "token function"
            },
            "unregister"
          ],
          [
            "span",
            {
              "class": "token punctuation"
            },
            "("
          ],
          [
            "span",
            {
              "class": "token string"
            },
            "'_http._tcp.'"
          ],
          [
            "span",
            {
              "class": "token punctuation"
            },
            ","
          ],
          " ",
          [
            "span",
            {
              "class": "token string"
            },
            "'local.'"
          ],
          [
            "span",
            {
              "class": "token punctuation"
            },
            ","
          ],
          " ",
          [
            "span",
            {
              "class": "token string"
            },
            "'Becvert\\'s iPad'"
          ],
          [
            "span",
            {
              "class": "token punctuation"
            },
            ")"
          ],
          [
            "span",
            {
              "class": "token punctuation"
            },
            ";"
          ]
        ]
      ],
      "\n"
    ]
  ],
  "package": "@ionic-native/zeroconf",
  "cordova": "cordova-plugin-zeroconf",
  "capacitorIncompatible": false,
  "premierSlug": null,
  "template": "native",
  "headings": [],
  "pageClass": "page-native-zeroconf"
}
