{
  "title": "ion-route-redirect",
  "path": "/docs/api/route-redirect",
  "body": [
    "div",
    null,
    [
      "p",
      {
        "class": "intro"
      },
      "A route redirect can only be used with an ",
      [
        "code",
        null,
        "ion-router"
      ],
      " as a direct child of it."
    ],
    " ",
    [
      "blockquote",
      null,
      " ",
      [
        "p",
        null,
        "Note: this component should only be used with vanilla and Stencil JavaScript projects. For Angular projects, use ",
        [
          "stencil-route-link",
          {
            "url": "/docs/api/router-outlet"
          },
          [
            "code",
            null,
            "ion-router-outlet"
          ]
        ],
        " and the Angular router."
      ],
      " "
    ],
    " ",
    [
      "p",
      null,
      "The route redirect has two configurable properties:"
    ],
    " ",
    [
      "ul",
      null,
      " ",
      [
        "li",
        null,
        [
          "code",
          null,
          "from"
        ]
      ],
      " ",
      [
        "li",
        null,
        [
          "code",
          null,
          "to"
        ]
      ],
      " "
    ],
    " ",
    [
      "p",
      null,
      "It redirects \"from\" a URL \"to\" another URL. When the defined ",
      [
        "code",
        null,
        "ion-route-redirect"
      ],
      " rule matches, the router will redirect from the path specified in the ",
      [
        "code",
        null,
        "from"
      ],
      " property to the path in the ",
      [
        "code",
        null,
        "to"
      ],
      " property. In order for a redirect to occur the ",
      [
        "code",
        null,
        "from"
      ],
      " path needs to be an exact match to the navigated URL."
    ],
    " ",
    [
      "h2",
      {
        "id": "multiple-route-redirects"
      },
      " ",
      [
        "a",
        {
          "href": "#multiple-route-redirects"
        },
        "Multiple Route Redirects"
      ],
      " "
    ],
    " ",
    [
      "p",
      null,
      "An arbitrary number of redirect routes can be defined inside an ",
      [
        "code",
        null,
        "ion-router"
      ],
      ", but only one can match."
    ],
    " ",
    [
      "p",
      null,
      "A route redirect will never call another redirect after its own redirect, since this could lead to infinite loops."
    ],
    " ",
    [
      "p",
      null,
      "Take the following two redirects:"
    ],
    " ",
    [
      "docs-code",
      {
        "language": "html"
      },
      " ",
      [
        "pre",
        null,
        [
          "code",
          null,
          [
            "span",
            {
              "class": "token tag"
            },
            [
              "span",
              {
                "class": "token tag"
              },
              [
                "span",
                {
                  "class": "token punctuation"
                },
                "<"
              ],
              "ion-router"
            ],
            [
              "span",
              {
                "class": "token punctuation"
              },
              ">"
            ]
          ],
          "\n  ",
          [
            "span",
            {
              "class": "token tag"
            },
            [
              "span",
              {
                "class": "token tag"
              },
              [
                "span",
                {
                  "class": "token punctuation"
                },
                "<"
              ],
              "ion-route-redirect"
            ],
            " ",
            [
              "span",
              {
                "class": "token attr-name"
              },
              "from"
            ],
            [
              "span",
              {
                "class": "token attr-value"
              },
              [
                "span",
                {
                  "class": "token punctuation"
                },
                "="
              ],
              [
                "span",
                {
                  "class": "token punctuation"
                },
                "\""
              ],
              "/admin",
              [
                "span",
                {
                  "class": "token punctuation"
                },
                "\""
              ]
            ],
            " ",
            [
              "span",
              {
                "class": "token attr-name"
              },
              "to"
            ],
            [
              "span",
              {
                "class": "token attr-value"
              },
              [
                "span",
                {
                  "class": "token punctuation"
                },
                "="
              ],
              [
                "span",
                {
                  "class": "token punctuation"
                },
                "\""
              ],
              "/login",
              [
                "span",
                {
                  "class": "token punctuation"
                },
                "\""
              ]
            ],
            [
              "span",
              {
                "class": "token punctuation"
              },
              ">"
            ]
          ],
          [
            "span",
            {
              "class": "token tag"
            },
            [
              "span",
              {
                "class": "token tag"
              },
              [
                "span",
                {
                  "class": "token punctuation"
                },
                "</"
              ],
              "ion-route-redirect"
            ],
            [
              "span",
              {
                "class": "token punctuation"
              },
              ">"
            ]
          ],
          "\n  ",
          [
            "span",
            {
              "class": "token tag"
            },
            [
              "span",
              {
                "class": "token tag"
              },
              [
                "span",
                {
                  "class": "token punctuation"
                },
                "<"
              ],
              "ion-route-redirect"
            ],
            " ",
            [
              "span",
              {
                "class": "token attr-name"
              },
              "from"
            ],
            [
              "span",
              {
                "class": "token attr-value"
              },
              [
                "span",
                {
                  "class": "token punctuation"
                },
                "="
              ],
              [
                "span",
                {
                  "class": "token punctuation"
                },
                "\""
              ],
              "/login",
              [
                "span",
                {
                  "class": "token punctuation"
                },
                "\""
              ]
            ],
            " ",
            [
              "span",
              {
                "class": "token attr-name"
              },
              "to"
            ],
            [
              "span",
              {
                "class": "token attr-value"
              },
              [
                "span",
                {
                  "class": "token punctuation"
                },
                "="
              ],
              [
                "span",
                {
                  "class": "token punctuation"
                },
                "\""
              ],
              "/admin",
              [
                "span",
                {
                  "class": "token punctuation"
                },
                "\""
              ]
            ],
            [
              "span",
              {
                "class": "token punctuation"
              },
              ">"
            ]
          ],
          [
            "span",
            {
              "class": "token tag"
            },
            [
              "span",
              {
                "class": "token tag"
              },
              [
                "span",
                {
                  "class": "token punctuation"
                },
                "</"
              ],
              "ion-route-redirect"
            ],
            [
              "span",
              {
                "class": "token punctuation"
              },
              ">"
            ]
          ],
          "\n",
          [
            "span",
            {
              "class": "token tag"
            },
            [
              "span",
              {
                "class": "token tag"
              },
              [
                "span",
                {
                  "class": "token punctuation"
                },
                "</"
              ],
              "ion-router"
            ],
            [
              "span",
              {
                "class": "token punctuation"
              },
              ">"
            ]
          ]
        ]
      ],
      " "
    ],
    " ",
    [
      "p",
      null,
      "If the user navigates to ",
      [
        "code",
        null,
        "/admin"
      ],
      " the router will redirect to ",
      [
        "code",
        null,
        "/login"
      ],
      " and stop there. It will never evaluate more than one redirect."
    ]
  ],
  "usage": {
    "javascript": [
      "div",
      null,
      [
        "docs-code",
        {
          "language": "html"
        },
        "\n  ",
        [
          "pre",
          null,
          [
            "code",
            null,
            [
              "span",
              {
                "class": "token comment"
              },
              "<!-- Redirects when the user navigates to `/admin` but\nwill NOT redirect if the user navigates to `/admin/posts` -->"
            ],
            "\n",
            [
              "span",
              {
                "class": "token tag"
              },
              [
                "span",
                {
                  "class": "token tag"
                },
                [
                  "span",
                  {
                    "class": "token punctuation"
                  },
                  "<"
                ],
                "ion-route-redirect"
              ],
              " ",
              [
                "span",
                {
                  "class": "token attr-name"
                },
                "from"
              ],
              [
                "span",
                {
                  "class": "token attr-value"
                },
                [
                  "span",
                  {
                    "class": "token punctuation"
                  },
                  "="
                ],
                [
                  "span",
                  {
                    "class": "token punctuation"
                  },
                  "\""
                ],
                "/admin",
                [
                  "span",
                  {
                    "class": "token punctuation"
                  },
                  "\""
                ]
              ],
              " ",
              [
                "span",
                {
                  "class": "token attr-name"
                },
                "to"
              ],
              [
                "span",
                {
                  "class": "token attr-value"
                },
                [
                  "span",
                  {
                    "class": "token punctuation"
                  },
                  "="
                ],
                [
                  "span",
                  {
                    "class": "token punctuation"
                  },
                  "\""
                ],
                "/login",
                [
                  "span",
                  {
                    "class": "token punctuation"
                  },
                  "\""
                ]
              ],
              [
                "span",
                {
                  "class": "token punctuation"
                },
                ">"
              ]
            ],
            [
              "span",
              {
                "class": "token tag"
              },
              [
                "span",
                {
                  "class": "token tag"
                },
                [
                  "span",
                  {
                    "class": "token punctuation"
                  },
                  "</"
                ],
                "ion-route-redirect"
              ],
              [
                "span",
                {
                  "class": "token punctuation"
                },
                ">"
              ]
            ],
            "\n\n",
            [
              "span",
              {
                "class": "token comment"
              },
              "<!-- By adding the wilcard character (*), the redirect will match\nany subpath of admin -->"
            ],
            "\n",
            [
              "span",
              {
                "class": "token tag"
              },
              [
                "span",
                {
                  "class": "token tag"
                },
                [
                  "span",
                  {
                    "class": "token punctuation"
                  },
                  "<"
                ],
                "ion-route-redirect"
              ],
              " ",
              [
                "span",
                {
                  "class": "token attr-name"
                },
                "from"
              ],
              [
                "span",
                {
                  "class": "token attr-value"
                },
                [
                  "span",
                  {
                    "class": "token punctuation"
                  },
                  "="
                ],
                [
                  "span",
                  {
                    "class": "token punctuation"
                  },
                  "\""
                ],
                "/admin/*",
                [
                  "span",
                  {
                    "class": "token punctuation"
                  },
                  "\""
                ]
              ],
              " ",
              [
                "span",
                {
                  "class": "token attr-name"
                },
                "to"
              ],
              [
                "span",
                {
                  "class": "token attr-value"
                },
                [
                  "span",
                  {
                    "class": "token punctuation"
                  },
                  "="
                ],
                [
                  "span",
                  {
                    "class": "token punctuation"
                  },
                  "\""
                ],
                "/login",
                [
                  "span",
                  {
                    "class": "token punctuation"
                  },
                  "\""
                ]
              ],
              [
                "span",
                {
                  "class": "token punctuation"
                },
                ">"
              ]
            ],
            [
              "span",
              {
                "class": "token tag"
              },
              [
                "span",
                {
                  "class": "token tag"
                },
                [
                  "span",
                  {
                    "class": "token punctuation"
                  },
                  "</"
                ],
                "ion-route-redirect"
              ],
              [
                "span",
                {
                  "class": "token punctuation"
                },
                ">"
              ]
            ]
          ]
        ],
        "\n"
      ],
      "\n\n    ",
      [
        "h3",
        {
          "id": "route-redirects-as-guards"
        },
        "\n      ",
        [
          "a",
          {
            "href": "#route-redirects-as-guards"
          },
          "Route Redirects as Guards"
        ],
        "\n    "
      ],
      "\n  ",
      [
        "p",
        null,
        "Redirection routes can work as guards to prevent users from navigating to certain areas of an application based on a given condition, such as if the user is authenticated or not."
      ],
      "\n",
      [
        "p",
        null,
        "A route redirect can be added and removed dynamically to redirect (or guard) some routes from being accessed. In the following example, all urls ",
        [
          "code",
          null,
          "*"
        ],
        " will be redirected to the ",
        [
          "code",
          null,
          "/login"
        ],
        " url if ",
        [
          "code",
          null,
          "isLoggedIn"
        ],
        " is ",
        [
          "code",
          null,
          "false"
        ],
        "."
      ],
      "\n\n",
      [
        "docs-code",
        {
          "language": "tsx"
        },
        "\n  ",
        [
          "pre",
          null,
          [
            "code",
            null,
            [
              "span",
              {
                "class": "token keyword"
              },
              "const"
            ],
            " isLoggedIn ",
            [
              "span",
              {
                "class": "token operator"
              },
              "="
            ],
            " ",
            [
              "span",
              {
                "class": "token boolean"
              },
              "false"
            ],
            [
              "span",
              {
                "class": "token punctuation"
              },
              ";"
            ],
            "\n\n",
            [
              "span",
              {
                "class": "token keyword"
              },
              "const"
            ],
            " router ",
            [
              "span",
              {
                "class": "token operator"
              },
              "="
            ],
            " document",
            [
              "span",
              {
                "class": "token punctuation"
              },
              "."
            ],
            [
              "span",
              {
                "class": "token function"
              },
              "querySelector"
            ],
            [
              "span",
              {
                "class": "token punctuation"
              },
              "("
            ],
            [
              "span",
              {
                "class": "token string"
              },
              "'ion-router'"
            ],
            [
              "span",
              {
                "class": "token punctuation"
              },
              ")"
            ],
            [
              "span",
              {
                "class": "token punctuation"
              },
              ";"
            ],
            "\n",
            [
              "span",
              {
                "class": "token keyword"
              },
              "const"
            ],
            " routeRedirect ",
            [
              "span",
              {
                "class": "token operator"
              },
              "="
            ],
            " document",
            [
              "span",
              {
                "class": "token punctuation"
              },
              "."
            ],
            [
              "span",
              {
                "class": "token function"
              },
              "createElement"
            ],
            [
              "span",
              {
                "class": "token punctuation"
              },
              "("
            ],
            [
              "span",
              {
                "class": "token string"
              },
              "'ion-route-redirect'"
            ],
            [
              "span",
              {
                "class": "token punctuation"
              },
              ")"
            ],
            [
              "span",
              {
                "class": "token punctuation"
              },
              ";"
            ],
            "\nrouteRedirect",
            [
              "span",
              {
                "class": "token punctuation"
              },
              "."
            ],
            [
              "span",
              {
                "class": "token function"
              },
              "setAttribute"
            ],
            [
              "span",
              {
                "class": "token punctuation"
              },
              "("
            ],
            [
              "span",
              {
                "class": "token string"
              },
              "'from'"
            ],
            [
              "span",
              {
                "class": "token punctuation"
              },
              ","
            ],
            " ",
            [
              "span",
              {
                "class": "token string"
              },
              "'*'"
            ],
            [
              "span",
              {
                "class": "token punctuation"
              },
              ")"
            ],
            [
              "span",
              {
                "class": "token punctuation"
              },
              ";"
            ],
            "\nrouteRedirect",
            [
              "span",
              {
                "class": "token punctuation"
              },
              "."
            ],
            [
              "span",
              {
                "class": "token function"
              },
              "setAttribute"
            ],
            [
              "span",
              {
                "class": "token punctuation"
              },
              "("
            ],
            [
              "span",
              {
                "class": "token string"
              },
              "'to'"
            ],
            [
              "span",
              {
                "class": "token punctuation"
              },
              ","
            ],
            " ",
            [
              "span",
              {
                "class": "token string"
              },
              "'/login'"
            ],
            [
              "span",
              {
                "class": "token punctuation"
              },
              ")"
            ],
            [
              "span",
              {
                "class": "token punctuation"
              },
              ";"
            ],
            "\n\n",
            [
              "span",
              {
                "class": "token keyword"
              },
              "if"
            ],
            " ",
            [
              "span",
              {
                "class": "token punctuation"
              },
              "("
            ],
            [
              "span",
              {
                "class": "token operator"
              },
              "!"
            ],
            "isLoggedIn",
            [
              "span",
              {
                "class": "token punctuation"
              },
              ")"
            ],
            " ",
            [
              "span",
              {
                "class": "token punctuation"
              },
              "{"
            ],
            "\n  router",
            [
              "span",
              {
                "class": "token punctuation"
              },
              "."
            ],
            [
              "span",
              {
                "class": "token function"
              },
              "appendChild"
            ],
            [
              "span",
              {
                "class": "token punctuation"
              },
              "("
            ],
            "routeRedirect",
            [
              "span",
              {
                "class": "token punctuation"
              },
              ")"
            ],
            [
              "span",
              {
                "class": "token punctuation"
              },
              ";"
            ],
            "\n",
            [
              "span",
              {
                "class": "token punctuation"
              },
              "}"
            ]
          ]
        ],
        "\n"
      ],
      "\n",
      [
        "p",
        null,
        "Alternatively, the value of ",
        [
          "code",
          null,
          "to"
        ],
        " can be modified based on a condition. In the following example, the route redirect will check if the user is logged in and redirect to the ",
        [
          "code",
          null,
          "/login"
        ],
        " url if not."
      ],
      "\n\n",
      [
        "docs-code",
        {
          "language": "html"
        },
        "\n  ",
        [
          "pre",
          null,
          [
            "code",
            null,
            [
              "span",
              {
                "class": "token tag"
              },
              [
                "span",
                {
                  "class": "token tag"
                },
                [
                  "span",
                  {
                    "class": "token punctuation"
                  },
                  "<"
                ],
                "ion-route-redirect"
              ],
              " ",
              [
                "span",
                {
                  "class": "token attr-name"
                },
                "id"
              ],
              [
                "span",
                {
                  "class": "token attr-value"
                },
                [
                  "span",
                  {
                    "class": "token punctuation"
                  },
                  "="
                ],
                [
                  "span",
                  {
                    "class": "token punctuation"
                  },
                  "\""
                ],
                "tutorialRedirect",
                [
                  "span",
                  {
                    "class": "token punctuation"
                  },
                  "\""
                ]
              ],
              " ",
              [
                "span",
                {
                  "class": "token attr-name"
                },
                "from"
              ],
              [
                "span",
                {
                  "class": "token attr-value"
                },
                [
                  "span",
                  {
                    "class": "token punctuation"
                  },
                  "="
                ],
                [
                  "span",
                  {
                    "class": "token punctuation"
                  },
                  "\""
                ],
                "*",
                [
                  "span",
                  {
                    "class": "token punctuation"
                  },
                  "\""
                ]
              ],
              [
                "span",
                {
                  "class": "token punctuation"
                },
                ">"
              ]
            ],
            [
              "span",
              {
                "class": "token tag"
              },
              [
                "span",
                {
                  "class": "token tag"
                },
                [
                  "span",
                  {
                    "class": "token punctuation"
                  },
                  "</"
                ],
                "ion-route-redirect"
              ],
              [
                "span",
                {
                  "class": "token punctuation"
                },
                ">"
              ]
            ]
          ]
        ],
        "\n"
      ],
      "\n\n",
      [
        "docs-code",
        {
          "language": "javascript"
        },
        "\n  ",
        [
          "pre",
          null,
          [
            "code",
            null,
            [
              "span",
              {
                "class": "token keyword"
              },
              "const"
            ],
            " isLoggedIn ",
            [
              "span",
              {
                "class": "token operator"
              },
              "="
            ],
            " ",
            [
              "span",
              {
                "class": "token boolean"
              },
              "false"
            ],
            [
              "span",
              {
                "class": "token punctuation"
              },
              ";"
            ],
            "\n",
            [
              "span",
              {
                "class": "token keyword"
              },
              "const"
            ],
            " routeRedirect ",
            [
              "span",
              {
                "class": "token operator"
              },
              "="
            ],
            " document",
            [
              "span",
              {
                "class": "token punctuation"
              },
              "."
            ],
            [
              "span",
              {
                "class": "token function"
              },
              "querySelector"
            ],
            [
              "span",
              {
                "class": "token punctuation"
              },
              "("
            ],
            [
              "span",
              {
                "class": "token string"
              },
              "'#tutorialRedirect'"
            ],
            [
              "span",
              {
                "class": "token punctuation"
              },
              ")"
            ],
            [
              "span",
              {
                "class": "token punctuation"
              },
              ";"
            ],
            "\n\nrouteRedirect",
            [
              "span",
              {
                "class": "token punctuation"
              },
              "."
            ],
            [
              "span",
              {
                "class": "token function"
              },
              "setAttribute"
            ],
            [
              "span",
              {
                "class": "token punctuation"
              },
              "("
            ],
            [
              "span",
              {
                "class": "token string"
              },
              "'to'"
            ],
            [
              "span",
              {
                "class": "token punctuation"
              },
              ","
            ],
            " isLoggedIn ",
            [
              "span",
              {
                "class": "token operator"
              },
              "?"
            ],
            " ",
            [
              "span",
              {
                "class": "token keyword"
              },
              "undefined"
            ],
            " ",
            [
              "span",
              {
                "class": "token operator"
              },
              ":"
            ],
            " ",
            [
              "span",
              {
                "class": "token string"
              },
              "'/login'"
            ],
            [
              "span",
              {
                "class": "token punctuation"
              },
              ")"
            ],
            [
              "span",
              {
                "class": "token punctuation"
              },
              ";"
            ]
          ]
        ],
        "\n"
      ]
    ]
  },
  "props": [
    {
      "name": "from",
      "type": "string",
      "mutable": false,
      "attr": "from",
      "reflectToAttr": false,
      "docs": "<p>A redirect route, redirects &quot;from&quot; a URL &quot;to&quot; another URL. This property is that &quot;from&quot; URL.\nIt needs to be an exact match of the navigated URL in order to apply.</p>\n<p>The path specified in this value is always an absolute path, even if the initial <code>/</code> slash\nis not specified.</p>\n",
      "docsTags": [],
      "values": [
        {
          "type": "string"
        }
      ],
      "optional": false,
      "required": true
    },
    {
      "name": "to",
      "type": "null | string | undefined",
      "mutable": false,
      "attr": "to",
      "reflectToAttr": false,
      "docs": "<p>A redirect route, redirects &quot;from&quot; a URL &quot;to&quot; another URL. This property is that &quot;to&quot; URL.\nWhen the defined <code>ion-route-redirect</code> rule matches, the router will redirect to the path\nspecified in this property.</p>\n<p>The value of this property is always an absolute path inside the scope of routes defined in\n<code>ion-router</code> it can&#39;t be used with another router or to perform a redirection to a different domain.</p>\n<p>Note that this is a virtual redirect, it will not cause a real browser refresh, again, it&#39;s\na redirect inside the context of ion-router.</p>\n<p>When this property is not specified or his value is <code>undefined</code> the whole redirect route is noop,\neven if the &quot;from&quot; value matches.</p>\n",
      "docsTags": [],
      "values": [
        {
          "type": "null"
        },
        {
          "type": "string"
        },
        {
          "type": "undefined"
        }
      ],
      "optional": false,
      "required": true
    }
  ],
  "methods": [],
  "template": "api",
  "filePath": "./src/components/route-redirect/route-redirect.tsx",
  "encapsulation": "none",
  "tag": "ion-route-redirect",
  "docs": [
    "div",
    null,
    "A route redirect can only be used with an `ion-router` as a direct child of it.\n\n> Note: this component should only be used with vanilla and Stencil JavaScript projects. For Angular projects, use [`ion-router-outlet`](../router-outlet) and the Angular router.\n\nThe route redirect has two configurable properties:\n - `from`\n - `to`\n\nIt redirects \"from\" a URL \"to\" another URL. When the defined `ion-route-redirect` rule matches, the router will redirect from the path specified in the `from` property to the path in the `to` property. In order for a redirect to occur the `from` path needs to be an exact match to the navigated URL."
  ],
  "docsTags": [],
  "events": [
    {
      "event": "ionRouteRedirectChanged",
      "detail": "any",
      "bubbles": true,
      "cancelable": true,
      "composed": true,
      "docs": "Internal event that fires when any value of this rule is added/removed from the DOM,\nor any of his public properties changes.\n\n`ion-router` captures this event in order to update his internal registry of router rules.",
      "docsTags": []
    }
  ],
  "listeners": [],
  "styles": [],
  "slots": [],
  "dependents": [],
  "dependencies": [],
  "dependencyGraph": {},
  "headings": [
    {
      "text": "Multiple Route Redirects",
      "href": "#multiple-route-redirects"
    }
  ],
  "pageClass": "page-api-route-redirect"
}
